BermiInflector/Inflector.py
BermiInflector/__init__.py
BermiInflector/tests.py
BermiInflector/Rules/Base.py
BermiInflector/Rules/English.py
BermiInflector/Rules/__init__.py
twistar/__init__.py
twistar/dbobject.py
twistar/exceptions.py
twistar/registry.py
twistar/relationships.py
twistar/utils.py
twistar/validation.py
twistar/dbconfig/__init__.py
twistar/dbconfig/base.py
twistar/dbconfig/mysql.py
twistar/dbconfig/postgres.py
twistar/dbconfig/pyodbc.py
twistar/dbconfig/sqlite.py
twistar/tests/__init__.py
twistar/tests/mysql_config.py
twistar/tests/postgres_config.py
twistar/tests/sqlite_config.py
twistar/tests/test_dbconfig.py
twistar/tests/test_dbobject.py
twistar/tests/test_relationships.py
twistar/tests/test_transactions.py
twistar/tests/test_utils.py
twistar/tests/utils.py
twistar-2.0.dist-info/METADATA
twistar-2.0.dist-info/RECORD
twistar-2.0.dist-info/WHEEL
twistar-2.0.dist-info/top_level.txt
