Metadata-Version: 2.1
Name: twistar
Version: 2.0
Summary: An implementation of the Active Record pattern for Twisted
Home-page: http://findingscience.com/twistar
Author: Brian Muller
Author-email: bamuller@gmail.com
License: MIT
Platform: UNKNOWN
Requires-Dist: twisted (>=12.1)
Requires-Dist: six
